[
  {
    "policy_id": "p_n_001",
    "tenant_id": "t_broker_north",
    "client_id": "c_n_001",
    "assigned_user_id": "u_north_agent_1",
    "policy_type": "home",
    "status": "active",
    "annual_premium": 640,
    "start_date": "2024-02-10",
    "end_date": "2025-02-09"
  },
  {
    "policy_id": "p_n_002",
    "tenant_id": "t_broker_north",
    "client_id": "c_n_002",
    "assigned_user_id": "u_north_agent_1",
    "policy_type": "health",
    "status": "active",
    "annual_premium": 1180,
    "start_date": "2024-02-15",
    "end_date": "2025-02-14"
  },
  {
    "policy_id": "p_n_003",
    "tenant_id": "t_broker_north",
    "client_id": "c_n_003",
    "assigned_user_id": "u_north_agent_2",
    "policy_type": "car",
    "status": "active",
    "annual_premium": 890,
    "start_date": "2024-03-10",
    "end_date": "2025-03-09"
  },
  {
    "policy_id": "p_n_004",
    "tenant_id": "t_broker_north",
    "client_id": "c_n_004",
    "assigned_user_id": "u_north_agent_2",
    "policy_type": "life",
    "status": "active",
    "annual_premium": 2100,
    "start_date": "2024-03-22",
    "end_date": "2025-03-21"
  },
  {
    "policy_id": "p_n_005",
    "tenant_id": "t_broker_north",
    "client_id": "c_n_005",
    "assigned_user_id": "u_north_agent_1",
    "policy_type": "commerce",
    "status": "active",
    "annual_premium": 1760,
    "start_date": "2024-04-11",
    "end_date": "2025-04-10"
  },
  {
    "policy_id": "p_n_006",
    "tenant_id": "t_broker_north",
    "client_id": "c_n_006",
    "assigned_user_id": "u_north_agent_2",
    "policy_type": "home",
    "status": "active",
    "annual_premium": 590,
    "start_date": "2024-04-20",
    "end_date": "2025-04-19"
  },
  {
    "policy_id": "p_n_007",
    "tenant_id": "t_broker_north",
    "client_id": "c_n_007",
    "assigned_user_id": "u_north_agent_1",
    "policy_type": "life",
    "status": "active",
    "annual_premium": 2650,
    "start_date": "2024-05-05",
    "end_date": "2025-05-04"
  },
  {
    "policy_id": "p_n_008",
    "tenant_id": "t_broker_north",
    "client_id": "c_n_008",
    "assigned_user_id": "u_north_agent_2",
    "policy_type": "commerce",
    "status": "active",
    "annual_premium": 1490,
    "start_date": "2024-05-14",
    "end_date": "2025-05-13"
  },
  {
    "policy_id": "p_n_009",
    "tenant_id": "t_broker_north",
    "client_id": "c_n_009",
    "assigned_user_id": "u_north_agent_1",
    "policy_type": "health",
    "status": "active",
    "annual_premium": 1320,
    "start_date": "2024-05-24",
    "end_date": "2025-05-23"
  },
  {
    "policy_id": "p_n_010",
    "tenant_id": "t_broker_north",
    "client_id": "c_n_010",
    "assigned_user_id": "u_north_agent_2",
    "policy_type": "car",
    "status": "active",
    "annual_premium": 830,
    "start_date": "2024-06-04",
    "end_date": "2025-06-03"
  },
  {
    "policy_id": "p_n_011",
    "tenant_id": "t_broker_north",
    "client_id": "c_n_002",
    "assigned_user_id": "u_north_agent_1",
    "policy_type": "car",
    "status": "cancelled",
    "annual_premium": 720,
    "start_date": "2023-01-01",
    "end_date": "2023-12-31"
  },
  {
    "policy_id": "p_n_012",
    "tenant_id": "t_broker_north",
    "client_id": "c_n_005",
    "assigned_user_id": "u_north_agent_1",
    "policy_type": "cyber",
    "status": "active",
    "annual_premium": 980,
    "start_date": "2024-06-10",
    "end_date": "2025-06-09"
  },
  {
    "policy_id": "p_n_013",
    "tenant_id": "t_broker_north",
    "client_id": "c_n_009",
    "assigned_user_id": "u_north_agent_1",
    "policy_type": "commerce",
    "status": "active",
    "annual_premium": 1540,
    "start_date": "2024-06-14",
    "end_date": "2025-06-13"
  },
  {
    "policy_id": "p_e_001",
    "tenant_id": "t_broker_east",
    "client_id": "c_e_001",
    "assigned_user_id": "u_east_agent_1",
    "policy_type": "home",
    "status": "active",
    "annual_premium": 610,
    "start_date": "2024-02-12",
    "end_date": "2025-02-11"
  },
  {
    "policy_id": "p_e_002",
    "tenant_id": "t_broker_east",
    "client_id": "c_e_002",
    "assigned_user_id": "u_east_agent_1",
    "policy_type": "life",
    "status": "active",
    "annual_premium": 2400,
    "start_date": "2024-02-20",
    "end_date": "2025-02-19"
  },
  {
    "policy_id": "p_e_003",
    "tenant_id": "t_broker_east",
    "client_id": "c_e_003",
    "assigned_user_id": "u_east_agent_2",
    "policy_type": "commerce",
    "status": "active",
    "annual_premium": 1690,
    "start_date": "2024-03-12",
    "end_date": "2025-03-11"
  },
  {
    "policy_id": "p_e_004",
    "tenant_id": "t_broker_east",
    "client_id": "c_e_004",
    "assigned_user_id": "u_east_agent_2",
    "policy_type": "health",
    "status": "active",
    "annual_premium": 980,
    "start_date": "2024-03-25",
    "end_date": "2025-03-24"
  },
  {
    "policy_id": "p_e_005",
    "tenant_id": "t_broker_east",
    "client_id": "c_e_005",
    "assigned_user_id": "u_east_agent_1",
    "policy_type": "car",
    "status": "active",
    "annual_premium": 810,
    "start_date": "2024-04-05",
    "end_date": "2025-04-04"
  },
  {
    "policy_id": "p_e_006",
    "tenant_id": "t_broker_east",
    "client_id": "c_e_006",
    "assigned_user_id": "u_east_agent_2",
    "policy_type": "home",
    "status": "active",
    "annual_premium": 560,
    "start_date": "2024-04-17",
    "end_date": "2025-04-16"
  },
  {
    "policy_id": "p_e_007",
    "tenant_id": "t_broker_east",
    "client_id": "c_e_007",
    "assigned_user_id": "u_east_agent_1",
    "policy_type": "commerce",
    "status": "active",
    "annual_premium": 1580,
    "start_date": "2024-05-04",
    "end_date": "2025-05-03"
  },
  {
    "policy_id": "p_e_008",
    "tenant_id": "t_broker_east",
    "client_id": "c_e_008",
    "assigned_user_id": "u_east_agent_2",
    "policy_type": "life",
    "status": "active",
    "annual_premium": 2210,
    "start_date": "2024-05-12",
    "end_date": "2025-05-11"
  },
  {
    "policy_id": "p_e_009",
    "tenant_id": "t_broker_east",
    "client_id": "c_e_009",
    "assigned_user_id": "u_east_agent_1",
    "policy_type": "health",
    "status": "active",
    "annual_premium": 1110,
    "start_date": "2024-05-24",
    "end_date": "2025-05-23"
  },
  {
    "policy_id": "p_e_010",
    "tenant_id": "t_broker_east",
    "client_id": "c_e_010",
    "assigned_user_id": "u_east_agent_2",
    "policy_type": "car",
    "status": "active",
    "annual_premium": 870,
    "start_date": "2024-06-06",
    "end_date": "2025-06-05"
  },
  {
    "policy_id": "p_e_011",
    "tenant_id": "t_broker_east",
    "client_id": "c_e_003",
    "assigned_user_id": "u_east_agent_2",
    "policy_type": "cyber",
    "status": "active",
    "annual_premium": 920,
    "start_date": "2024-06-15",
    "end_date": "2025-06-14"
  },
  {
    "policy_id": "p_e_012",
    "tenant_id": "t_broker_east",
    "client_id": "c_e_007",
    "assigned_user_id": "u_east_agent_1",
    "policy_type": "commerce",
    "status": "cancelled",
    "annual_premium": 1490,
    "start_date": "2023-03-01",
    "end_date": "2024-02-29"
  },
  {
    "policy_id": "p_e_013",
    "tenant_id": "t_broker_east",
    "client_id": "c_e_010",
    "assigned_user_id": "u_east_agent_2",
    "policy_type": "health",
    "status": "active",
    "annual_premium": 990,
    "start_date": "2024-06-18",
    "end_date": "2025-06-17"
  }
]
